easyget/__init__.py
easyget/__main__.py
easyget-1.0.1.dist-info/licenses/LICENSE
easyget-1.0.1.dist-info/METADATA
easyget-1.0.1.dist-info/WHEEL
easyget-1.0.1.dist-info/entry_points.txt
easyget-1.0.1.dist-info/top_level.txt
easyget-1.0.1.dist-info/RECORD
