Metadata-Version: 2.4
Name: easyget
Version: 1.0.1
Summary: Fast, easy-to-use multi-platform file downloader
Author: Your Name
Classifier: Programming Language :: Python :: 3
Classifier: Operating System :: OS Independent
Requires-Python: >=3.7
License-File: LICENSE
Requires-Dist: httpx>=0.27.0
Requires-Dist: tqdm>=4.60.0
Dynamic: author
Dynamic: classifier
Dynamic: license-file
Dynamic: requires-dist
Dynamic: requires-python
Dynamic: summary
